{"nodes": [{"id": "backend_ai_app_agent_py", "label": "agent.py", "file_type": "code", "source_file": "backend-ai/app/agent.py", "source_location": "L1"}, {"id": "agent_entrypoint", "label": "entrypoint()", "file_type": "code", "source_file": "backend-ai/app/agent.py", "source_location": "L20"}], "edges": [{"source": "backend_ai_app_agent_py", "target": "logging", "relation": "imports", "confidence": "EXTRACTED", "source_file": "backend-ai/app/agent.py", "source_location": "L1", "weight": 1.0}, {"source": "backend_ai_app_agent_py", "target": "os", "relation": "imports", "confidence": "EXTRACTED", "source_file": "backend-ai/app/agent.py", "source_location": "L2", "weight": 1.0}, {"source": "backend_ai_app_agent_py", "target": "asyncio", "relation": "imports", "confidence": "EXTRACTED", "source_file": "backend-ai/app/agent.py", "source_location": "L3", "weight": 1.0}, {"source": "backend_ai_app_agent_py", "target": "json", "relation": "imports", "confidence": "EXTRACTED", "source_file": "backend-ai/app/agent.py", "source_location": "L4", "weight": 1.0}, {"source": "backend_ai_app_agent_py", "target": "dotenv", "relation": "imports_from", "confidence": "EXTRACTED", "source_file": "backend-ai/app/agent.py", "source_location": "L5", "weight": 1.0}, {"source": "backend_ai_app_agent_py", "target": "livekit", "relation": "imports_from", "confidence": "EXTRACTED", "source_file": "backend-ai/app/agent.py", "source_location": "L6", "weight": 1.0}, {"source": "backend_ai_app_agent_py", "target": "livekit_plugins", "relation": "imports_from", "confidence": "EXTRACTED", "source_file": "backend-ai/app/agent.py", "source_location": "L7", "weight": 1.0}, {"source": "backend_ai_app_agent_py", "target": "certifi", "relation": "imports", "confidence": "EXTRACTED", "source_file": "backend-ai/app/agent.py", "source_location": "L9", "weight": 1.0}, {"source": "backend_ai_app_agent_py", "target": "agent_entrypoint", "relation": "contains", "confidence": "EXTRACTED", "source_file": "backend-ai/app/agent.py", "source_location": "L20", "weight": 1.0}, {"source": "backend_ai_app_agent_py", "target": "asyncio", "relation": "imports", "confidence": "EXTRACTED", "source_file": "backend-ai/app/agent.py", "source_location": "L78", "weight": 1.0}, {"source": "backend_ai_app_agent_py", "target": "json", "relation": "imports", "confidence": "EXTRACTED", "source_file": "backend-ai/app/agent.py", "source_location": "L79", "weight": 1.0}]}